interaktiv.recommendations-1.0.3-py3.10-nspkg.pth
interaktiv/recommendations/__init__.py
interaktiv/recommendations/configure.zcml
interaktiv/recommendations/interfaces.py
interaktiv/recommendations/package.json
interaktiv/recommendations/setuphandlers.py
interaktiv/recommendations/testing.py
interaktiv/recommendations/behaviors/__init__.py
interaktiv/recommendations/behaviors/configure.zcml
interaktiv/recommendations/behaviors/recommendable.py
interaktiv/recommendations/controlpanels/__init__.py
interaktiv/recommendations/controlpanels/configure.zcml
interaktiv/recommendations/controlpanels/recommendations_settings.py
interaktiv/recommendations/controlpanels/widgets.py
interaktiv/recommendations/controlpanels/templates/recommendations_controlpanel_layout.pt
interaktiv/recommendations/controlpanels/templates/widget_info.pt
interaktiv/recommendations/controlpanels/templates/widget_refresh.pt
interaktiv/recommendations/controlpanels/templates/widget_testdata_import.pt
interaktiv/recommendations/locales/de/LC_MESSAGES/interaktiv.recommendations.mo
interaktiv/recommendations/locales/de/LC_MESSAGES/interaktiv.recommendations.po
interaktiv/recommendations/locales/en/LC_MESSAGES/interaktiv.recommendations.mo
interaktiv/recommendations/locales/en/LC_MESSAGES/interaktiv.recommendations.po
interaktiv/recommendations/profiles/default/browserlayer.xml
interaktiv/recommendations/profiles/default/catalog.xml
interaktiv/recommendations/profiles/default/controlpanel.xml
interaktiv/recommendations/profiles/default/metadata.xml
interaktiv/recommendations/profiles/default/registry.xml
interaktiv/recommendations/profiles/default/toolset.xml
interaktiv/recommendations/profiles/uninstall/browserlayer.xml
interaktiv/recommendations/profiles/uninstall/catalog.xml
interaktiv/recommendations/profiles/uninstall/controlpanel.xml
interaktiv/recommendations/profiles/uninstall/metadata.xml
interaktiv/recommendations/profiles/uninstall/toolset.xml
interaktiv/recommendations/restapi/__init__.py
interaktiv.recommendations-1.0.3.dist-info/LICENSE.md
interaktiv.recommendations-1.0.3.dist-info/METADATA
interaktiv.recommendations-1.0.3.dist-info/WHEEL
interaktiv.recommendations-1.0.3.dist-info/entry_points.txt
interaktiv.recommendations-1.0.3.dist-info/namespace_packages.txt
interaktiv.recommendations-1.0.3.dist-info/top_level.txt
interaktiv.recommendations-1.0.3.dist-info/RECORD
