Metadata-Version: 2.1
Name: interaktiv.recommendations
Version: 1.0.3
Summary: Interaktiv Recommendations product.
Home-page: https://code.interaktiv.de/interaktiv/interaktiv.recommendations
Author: Interaktiv
Author-email: support@interaktiv.de
License: BSD License (BSD)
Classifier: Environment :: Web Environment
Classifier: Framework :: Plone
Classifier: Framework :: Plone :: Addon
Classifier: Operating System :: OS Independent
Classifier: Programming Language :: Python
Classifier: Topic :: Software Development :: Libraries :: Python Modules
License-File: LICENSE.md
Requires-Dist: setuptools
Requires-Dist: plone.app.contenttypes
Requires-Dist: plone.app.testing
Requires-Dist: plone.restapi
Requires-Dist: plone.app.robotframework
Requires-Dist: sklearn (==0.0)
Requires-Dist: scikit-learn (==1.0.1)
Requires-Dist: scipy (==1.7.2)
Requires-Dist: threadpoolctl (==3.0.0)
Requires-Dist: joblib (==1.1.0)
Requires-Dist: numpy (==1.21.4)
Requires-Dist: pandas (==1.3.4)
Provides-Extra: test
Requires-Dist: unittest2 ; extra == 'test'
Requires-Dist: plone.testing ; extra == 'test'
Requires-Dist: plone.app.testing ; extra == 'test'
